calc_napa_py/__init__.py
calc_napa_py/calcClass.py
calc_package_napa-0.1.dist-info/METADATA
calc_package_napa-0.1.dist-info/WHEEL
calc_package_napa-0.1.dist-info/top_level.txt
calc_package_napa-0.1.dist-info/RECORD
