Metadata-Version: 2.1
Name: calc-package-napa
Version: 0.1
Summary: Simple calculator app
Home-page: UNKNOWN
Author: Kalpana
Author-email: kalpana_tella@yahoo.com
License: UNKNOWN
Platform: UNKNOWN
Requires-Python: >=3.6
